gameauto/__init__.py
gameauto/core.py
gameauto/images.py
gameauto-1.0.4.dist-info/METADATA
gameauto-1.0.4.dist-info/WHEEL
gameauto-1.0.4.dist-info/top_level.txt
gameauto-1.0.4.dist-info/RECORD
