Metadata-Version: 2.1
Name: gameauto
Version: 1.0.4
Summary: Android Game Auto Pypi
Home-page: https://github.com/NakanoSanku
Author: KateTseng
Author-email: Kate.TsengK@outlook.com
License: MIT
Keywords: game
Platform: UNKNOWN
Requires-Python: >=3
Requires-Dist: minidevice (>=1.0.4)
Requires-Dist: ncnn (>=1.0.20230517)
